README.md
setup.py
ciphers/__init__.py
ciphers/caeser_cipher.py
ciphers/cipher_helper.py
ciphers/vigenere_cipher.py
ron_cipher.egg-info/PKG-INFO
ron_cipher.egg-info/SOURCES.txt
ron_cipher.egg-info/dependency_links.txt
ron_cipher.egg-info/entry_points.txt
ron_cipher.egg-info/top_level.txt
tests/__init__.py
tests/test_caeser_cipher.py
tests/test_vignere_cipher.py