Metadata-Version: 2.1
Name: ron-cipher
Version: 1.0.3
Summary: A cipher package meant for CLI use to encrypt/decrypt using various ciphers
Home-page: https://github.com/nairraghav/ron-cipher
Author: Raghav Nair
Author-email: nairraghav@hotmail.com
License: UNKNOWN
Platform: UNKNOWN
Classifier: Programming Language :: Python :: 3
Classifier: License :: OSI Approved :: MIT License
Classifier: Operating System :: OS Independent
Requires-Python: >=3.6
